shapicant/__init__.py
shapicant/_base.py
shapicant/_pandas_selector.py
shapicant/_spark_selector.py
shapicant/_spark_udf_selector.py
shapicant/tests/__init__.py
shapicant/tests/test_selector.py
shapicant-0.4.0.dist-info/LICENSE
shapicant-0.4.0.dist-info/METADATA
shapicant-0.4.0.dist-info/WHEEL
shapicant-0.4.0.dist-info/top_level.txt
shapicant-0.4.0.dist-info/RECORD
