Metadata-Version: 2.1
Name: shapicant
Version: 0.4.0
Summary: Feature selection package based on SHAP and target permutation, for pandas and Spark
Home-page: https://github.com/manuel-calzolari/shapicant
Author: Manuel Calzolari
License: UNKNOWN
Download-URL: https://github.com/manuel-calzolari/shapicant/releases
Platform: UNKNOWN
Classifier: Development Status :: 4 - Beta
Classifier: Intended Audience :: Science/Research
Classifier: Intended Audience :: Developers
Classifier: Topic :: Software Development
Classifier: Topic :: Scientific/Engineering
Classifier: License :: OSI Approved :: MIT License
Classifier: Programming Language :: Python :: 3
Classifier: Programming Language :: Python :: 3.6
Classifier: Programming Language :: Python :: 3.7
Classifier: Programming Language :: Python :: 3.8
Requires-Python: >=3.6
Requires-Dist: shap (>=0.36.0)
Requires-Dist: numpy
Requires-Dist: pandas
Requires-Dist: scikit-learn
Requires-Dist: tqdm
Provides-Extra: spark
Requires-Dist: pyspark (>=3.0) ; extra == 'spark'
Requires-Dist: pyarrow ; extra == 'spark'
